[
  {"quote":"The best way to get started is to quit talking and begin doing.","author":"Walt Disney"},
  {"quote":"Don't let yesterday take up too much of today.","author":"Will Rogers"},
  {"quote":"It's not whether you get knocked down, it's whether you get up.","author":"Vince Lombardi"},
  {"quote":"If you are working on something exciting, it will keep you motivated.","author":"Unknown"},
  {"quote":"Success is not in what you have, but who you are.","author":"Bo Bennett"},
  {"quote":"The harder you work for something, the greater you'll feel when you achieve it.","author":"Unknown"},
  {"quote":"Dream bigger. Do bigger.","author":"Unknown"},
  {"quote":"Don’t watch the clock; do what it does. Keep going.","author":"Sam Levenson"},
  {"quote":"Great things never come from comfort zones.","author":"Unknown"},
  {"quote":"Push yourself, because no one else is going to do it for you.","author":"Unknown"},
  {"quote":"Sometimes later becomes never. Do it now.","author":"Unknown"},
  {"quote":"Don’t wait for opportunity. Create it.","author":"Unknown"},
  {"quote":"Little things make big days.","author":"Unknown"},
  {"quote":"It’s going to be hard, but hard does not mean impossible.","author":"Unknown"},
  {"quote":"Don’t stop when you’re tired. Stop when you’re done.","author":"Marilyn Monroe"},
  {"quote":"Wake up with determination. Go to bed with satisfaction.","author":"Unknown"},
  {"quote":"Do something today that your future self will thank you for.","author":"Unknown"},
  {"quote":"Sometimes we’re tested not to show our weaknesses, but to discover our strengths.","author":"Unknown"},
  {"quote":"The key to success is to focus on goals, not obstacles.","author":"Unknown"},
  {"quote":"Work hard in silence. Let success make the noise.","author":"Frank Ocean"},
  {"quote":"Opportunities don't happen. You create them.","author":"Chris Grosser"},
  {"quote":"Your limitation—it’s only your imagination.","author":"Unknown"},
  {"quote":"Sometimes you win, sometimes you learn.","author":"John Maxwell"},
  {"quote":"Don’t be afraid to give up the good to go for the great.","author":"John D. Rockefeller"},
  {"quote":"I find that the harder I work, the more luck I seem to have.","author":"Thomas Jefferson"},
  {"quote":"The secret of getting ahead is getting started.","author":"Mark Twain"},
  {"quote":"Do what you can with all you have, wherever you are.","author":"Theodore Roosevelt"},
  {"quote":"The only way to achieve the impossible is to believe it is possible.","author":"Charles Kingsleigh"},
  {"quote":"Don’t limit your challenges. Challenge your limits.","author":"Unknown"},
  {"quote":"Great things never came from comfort zones.","author":"Unknown"},
  {"quote":"Stay positive, work hard, make it happen.","author":"Unknown"},
  {"quote":"You don’t have to be great to start, but you have to start to be great.","author":"Zig Ziglar"},
  {"quote":"Everything you can imagine is real.","author":"Pablo Picasso"},
  {"quote":"Do one thing every day that scares you.","author":"Eleanor Roosevelt"},
  {"quote":"Failure will never overtake me if my determination to succeed is strong enough.","author":"Og Mandino"},
  {"quote":"The way to get started is to quit talking and begin doing.","author":"Walt Disney"},
  {"quote":"Don't let what you cannot do interfere with what you can do.","author":"John Wooden"},
  {"quote":"Motivation is what gets you started. Habit is what keeps you going.","author":"Jim Ryun"},
  {"quote":"It always seems impossible until it’s done.","author":"Nelson Mandela"},
  {"quote":"You are never too old to set another goal or to dream a new dream.","author":"C.S. Lewis"},
  {"quote":"If you want to lift yourself up, lift up someone else.","author":"Booker T. Washington"},
  {"quote":"Act as if what you do makes a difference. It does.","author":"William James"},
  {"quote":"Success usually comes to those who are too busy to be looking for it.","author":"Henry David Thoreau"},
  {"quote":"Keep your face always toward the sunshine—and shadows will fall behind you.","author":"Walt Whitman"},
  {"quote":"The only limit to our realization of tomorrow is our doubts of today.","author":"Franklin D. Roosevelt"},
  {"quote":"Hardships often prepare ordinary people for an extraordinary destiny.","author":"C.S. Lewis"},
  {"quote":"Don’t count the days, make the days count.","author":"Muhammad Ali"},
  {"quote":"If you can dream it, you can do it.","author":"Walt Disney"},
  {"quote":"In order to succeed, we must first believe that we can.","author":"Nikos Kazantzakis"},
  {"quote":"The best revenge is massive success.","author":"Frank Sinatra"},
  {"quote":"A year from now you may wish you had started today.","author":"Karen Lamb"},
  {"quote":"We generate fears while we sit. We overcome them by action.","author":"Dr. Henry Link"},
  {"quote":"Setting goals is the first step in turning the invisible into the visible.","author":"Tony Robbins"},
  {"quote":"Don’t be pushed around by the fears in your mind. Be led by the dreams in your heart.","author":"Roy T. Bennett"},
  {"quote":"Whatever you are, be a good one.","author":"Abraham Lincoln"},
  {"quote":"You miss 100% of the shots you don’t take.","author":"Wayne Gretzky"},
  {"quote":"The future belongs to those who believe in the beauty of their dreams.","author":"Eleanor Roosevelt"},
  {"quote":"Do not let what you cannot do interfere with what you can do.","author":"John Wooden"},
  {"quote":"Keep going. Be all in.","author":"Bryan Hutchinson"},
  {"quote":"You must do the thing you think you cannot do.","author":"Eleanor Roosevelt"},
  {"quote":"The secret to success is to know something nobody else knows.","author":"Aristotle Onassis"},
  {"quote":"Don’t wait. The time will never be just right.","author":"Napoleon Hill"},
  {"quote":"Be yourself; everyone else is already taken.","author":"Oscar Wilde"},
  {"quote":"The purpose of our lives is to be happy.","author":"Dalai Lama"},
  {"quote":"Believe you can and you're halfway there.","author":"Theodore Roosevelt"},
  {"quote":"Don’t let small minds convince you that your dreams are too big.","author":"Unknown"},
  {"quote":"Strive not to be a success, but rather to be of value.","author":"Albert Einstein"},
  {"quote":"Happiness is not something ready made. It comes from your own actions.","author":"Dalai Lama"},
  {"quote":"A person who never made a mistake never tried anything new.","author":"Albert Einstein"},
  {"quote":"The best dreams happen when you’re awake.","author":"Cherie Gilderbloom"},
  {"quote":"Do what you love, love what you do.","author":"Unknown"},
  {"quote":"Success is the sum of small efforts, repeated day in and day out.","author":"Robert Collier"},
  {"quote":"The mind is everything. What you think you become.","author":"Buddha"},
  {"quote":"It does not matter how slowly you go as long as you do not stop.","author":"Confucius"},
  {"quote":"Action is the foundational key to all success.","author":"Pablo Picasso"},
  {"quote":"Believe in yourself and all that you are.","author":"Christian Larson"},
  {"quote":"Don't let yesterday take up too much of today.","author":"Will Rogers"},
  {"quote":"Everything has beauty, but not everyone sees it.","author":"Confucius"},
  {"quote":"Do not go where the path may lead, go instead where there is no path and leave a trail.","author":"Ralph Waldo Emerson"},
  {"quote":"With the new day comes new strength and new thoughts.","author":"Eleanor Roosevelt"},
  {"quote":"Success is not final, failure is not fatal: It is the courage to continue that counts.","author":"Winston Churchill"},
  {"quote":"The only thing standing between you and your goal is the story you keep telling yourself as to why you can't achieve it.","author":"Jordan Belfort"},
  {"quote":"Start where you are. Use what you have. Do what you can.","author":"Arthur Ashe"},
  {"quote":"I never dreamed about success. I worked for it.","author":"Estee Lauder"},
  {"quote":"Don’t wait for opportunity. Create it.","author":"Unknown"},
  {"quote":"Whatever you do, do it well.","author":"Walt Disney"},
  {"quote":"The journey of a thousand miles begins with one step.","author":"Lao Tzu"},
  {"quote":"Fall seven times and stand up eight.","author":"Japanese Proverb"},
  {"quote":"The best way to predict the future is to create it.","author":"Peter Drucker"},
  {"quote":"Life is what happens when you’re busy making other plans.","author":"John Lennon"},
  {"quote":"Opportunities don't happen, you create them.","author":"Chris Grosser"},
  {"quote":"Don’t let what you cannot do stop you from doing what you can do.","author":"John Wooden"}
]
